numpyro/__init__.py
numpyro/_typing.py
numpyro/diagnostics.py
numpyro/handlers.py
numpyro/optim.py
numpyro/patch.py
numpyro/primitives.py
numpyro/util.py
numpyro/version.py
numpyro/compat/__init__.py
numpyro/compat/distributions.py
numpyro/compat/handlers.py
numpyro/compat/infer.py
numpyro/compat/ops.py
numpyro/compat/optim.py
numpyro/compat/pyro.py
numpyro/compat/util.py
numpyro/contrib/__init__.py
numpyro/contrib/ecs_proxies.py
numpyro/contrib/module.py
numpyro/contrib/nested_sampling.py
numpyro/contrib/render.py
numpyro/contrib/control_flow/__init__.py
numpyro/contrib/control_flow/cond.py
numpyro/contrib/control_flow/scan.py
numpyro/contrib/einstein/__init__.py
numpyro/contrib/einstein/mixture_guide_predictive.py
numpyro/contrib/einstein/stein_kernels.py
numpyro/contrib/einstein/stein_loss.py
numpyro/contrib/einstein/stein_util.py
numpyro/contrib/einstein/steinvi.py
numpyro/contrib/funsor/__init__.py
numpyro/contrib/funsor/discrete.py
numpyro/contrib/funsor/enum_messenger.py
numpyro/contrib/funsor/infer_util.py
numpyro/contrib/hsgp/__init__.py
numpyro/contrib/hsgp/approximation.py
numpyro/contrib/hsgp/laplacian.py
numpyro/contrib/hsgp/spectral_densities.py
numpyro/contrib/stochastic_support/__init__.py
numpyro/contrib/stochastic_support/dcc.py
numpyro/contrib/stochastic_support/sdvi.py
numpyro/contrib/tfp/__init__.py
numpyro/contrib/tfp/distributions.py
numpyro/contrib/tfp/mcmc.py
numpyro/distributions/__init__.py
numpyro/distributions/batch_util.py
numpyro/distributions/censored.py
numpyro/distributions/conjugate.py
numpyro/distributions/constraints.py
numpyro/distributions/continuous.py
numpyro/distributions/copula.py
numpyro/distributions/directional.py
numpyro/distributions/discrete.py
numpyro/distributions/distribution.py
numpyro/distributions/flows.py
numpyro/distributions/gof.py
numpyro/distributions/kl.py
numpyro/distributions/mixtures.py
numpyro/distributions/transforms.py
numpyro/distributions/truncated.py
numpyro/distributions/util.py
numpyro-0.20.0.dist-info/licenses/LICENSE.md
numpyro-0.20.0.dist-info/METADATA
numpyro-0.20.0.dist-info/WHEEL
numpyro-0.20.0.dist-info/top_level.txt
numpyro-0.20.0.dist-info/RECORD
