Metadata-Version: 2.4
Name: numpyro
Version: 0.20.0
Summary: Pyro PPL on NumPy
Home-page: https://github.com/pyro-ppl/numpyro
Author: Uber AI Labs
License: Apache License 2.0
Keywords: probabilistic machine learning bayesian statistics
Classifier: Intended Audience :: Developers
Classifier: Intended Audience :: Education
Classifier: Intended Audience :: Science/Research
Classifier: License :: OSI Approved :: Apache Software License
Classifier: Operating System :: POSIX :: Linux
Classifier: Operating System :: MacOS :: MacOS X
Classifier: Programming Language :: Python :: 3.11
Classifier: Programming Language :: Python :: 3.12
Classifier: Programming Language :: Python :: 3.13
Classifier: Programming Language :: Python :: 3.14
Requires-Python: >=3.9
License-File: LICENSE.md
Requires-Dist: jax>=0.7.0
Requires-Dist: jaxlib>=0.7.0
Requires-Dist: multipledispatch
Requires-Dist: numpy
Requires-Dist: tqdm
Provides-Extra: doc
Requires-Dist: ipython; extra == "doc"
Requires-Dist: nbsphinx>=0.8.9; extra == "doc"
Requires-Dist: readthedocs-sphinx-search>=0.3.2; extra == "doc"
Requires-Dist: sphinx>=5; extra == "doc"
Requires-Dist: sphinx_rtd_theme; extra == "doc"
Requires-Dist: sphinx-gallery; extra == "doc"
Provides-Extra: test
Requires-Dist: importlib-metadata<5.0; extra == "test"
Requires-Dist: ruff>=0.1.8; extra == "test"
Requires-Dist: mypy>=1.13; extra == "test"
Requires-Dist: pytest>=4.1; extra == "test"
Requires-Dist: pyro-api>=0.1.1; extra == "test"
Requires-Dist: scikit-learn; extra == "test"
Requires-Dist: scipy>=1.9; extra == "test"
Requires-Dist: ty>=0.0.4; extra == "test"
Provides-Extra: dev
Requires-Dist: dm-haiku>=0.0.14; extra == "dev"
Requires-Dist: equinox; extra == "dev"
Requires-Dist: flax; extra == "dev"
Requires-Dist: funsor>=0.4.1; extra == "dev"
Requires-Dist: graphviz; extra == "dev"
Requires-Dist: jaxns<=2.6.9,>=2.6.3; extra == "dev"
Requires-Dist: matplotlib; extra == "dev"
Requires-Dist: optax>=0.0.6; extra == "dev"
Requires-Dist: pylab-sdk; extra == "dev"
Requires-Dist: pytest-cov; extra == "dev"
Requires-Dist: pyyaml; extra == "dev"
Requires-Dist: requests; extra == "dev"
Requires-Dist: tfp-nightly; extra == "dev"
Provides-Extra: examples
Requires-Dist: arviz; extra == "examples"
Requires-Dist: jupyter; extra == "examples"
Requires-Dist: matplotlib; extra == "examples"
Requires-Dist: pandas; extra == "examples"
Requires-Dist: seaborn; extra == "examples"
Requires-Dist: scikit-learn; extra == "examples"
Requires-Dist: wordcloud; extra == "examples"
Provides-Extra: cpu
Requires-Dist: jax[cpu]>=0.7.0; extra == "cpu"
Provides-Extra: tpu
Requires-Dist: jax[tpu]>=0.7.0; extra == "tpu"
Provides-Extra: cuda12
Requires-Dist: jax[cuda12]>=0.7.0; extra == "cuda12"
Provides-Extra: cuda13
Requires-Dist: jax[cuda13]>=0.7.0; extra == "cuda13"
Dynamic: author
Dynamic: classifier
Dynamic: description
Dynamic: description-content-type
Dynamic: home-page
Dynamic: keywords
Dynamic: license
Dynamic: license-file
Dynamic: provides-extra
Dynamic: requires-dist
Dynamic: requires-python
Dynamic: summary
